awschains/_version.py
awschains/dynamochain.py
awschains-0.0.3.dist-info/LICENSE
awschains-0.0.3.dist-info/METADATA
awschains-0.0.3.dist-info/WHEEL
awschains-0.0.3.dist-info/top_level.txt
awschains-0.0.3.dist-info/RECORD
