Metadata-Version: 2.1
Name: awschains
Version: 0.0.3
License: Apache License
Classifier: Programming Language :: Python :: 3.9
Requires-Python: ==3.9.*
License-File: LICENSE
Requires-Dist: boto3 (~=1.26)
Provides-Extra: dev
Requires-Dist: pytest ; extra == 'dev'
Requires-Dist: flake8 ; extra == 'dev'
Requires-Dist: mypy ; extra == 'dev'
Requires-Dist: black ; extra == 'dev'
Requires-Dist: isort ; extra == 'dev'
